eccontrib_sphinxdoc-0.0.3-py2.7-nspkg.pth
eccontrib/sphinxdoc.py
eccontrib_sphinxdoc-0.0.3.dist-info/AUTHORS.rst
eccontrib_sphinxdoc-0.0.3.dist-info/METADATA
eccontrib_sphinxdoc-0.0.3.dist-info/WHEEL
eccontrib_sphinxdoc-0.0.3.dist-info/namespace_packages.txt
eccontrib_sphinxdoc-0.0.3.dist-info/top_level.txt
eccontrib_sphinxdoc-0.0.3.dist-info/RECORD
