Metadata-Version: 2.1
Name: eccontrib-sphinxdoc
Version: 0.0.3
Summary: A sphinx extension for documenting ec based scripts.
Home-page: https://github.com/Laufire/ec/sphinxdoc
Author: Laufire Technologies
Author-email: laufiretechnologies@gmail.com
License: MIT
Download-URL: http://pypi.python.org/pypi/eccontrib-sphinxdoc
Keywords: sphinxdoc sphinx contrib extension laufire ec
Platform: any
Classifier: Development Status :: 2 - Pre-Alpha
Classifier: Environment :: Console
Classifier: Environment :: Web Environment
Classifier: Intended Audience :: Developers
Classifier: License :: OSI Approved :: MIT License
Classifier: Operating System :: OS Independent
Classifier: Programming Language :: Python
Classifier: Programming Language :: Python :: 2
Classifier: Programming Language :: Python :: 3
Classifier: Topic :: Documentation
Classifier: Topic :: Utilities
Classifier: Framework :: Sphinx
Classifier: Framework :: Sphinx :: Extension
Requires-Dist: ec (>=0.2.5)
Requires-Dist: Sphinx (>=1.2.3)
Requires-Dist: docutils (>=0.12)
